[
  {
    "make": "B & W CONSTRUCTION",
    "model": "B & W CONSTRUCTION TRAILER",
    "variant": "9000S/9000 TURBO 4DR HATCHBACK",
    "year": 1990,
    "curb_weight_tons": 1.5
  },
  {
    "make": "B & W CONSTRUCTION",
    "model": "B & W CONSTRUCTION TRAILER",
    "variant": "900S 2DR HATCHBACK",
    "year": 1990,
    "curb_weight_tons": 1.4
  },
  {
    "make": "B & W CONSTRUCTION",
    "model": "B & W CONSTRUCTION TRAILER",
    "variant": "JUSTY DL/GL/GL 4WD 2DR HATCHBACK",
    "year": 1990,
    "curb_weight_tons": 0.9
  },
  {
    "make": "B & W CONSTRUCTION",
    "model": "B & W CONSTRUCTION TRAILER",
    "variant": "JUSTY GL 4WD 4DR HATCHBACK",
    "year": 1990,
    "curb_weight_tons": 1.0
  },
  {
    "make": "B & W CONSTRUCTION",
    "model": "B & W CONSTRUCTION TRAILER",
    "variant": "BENTLEY MULSANNE/TURBO R 4DR SEDAN",
    "year": 1990,
    "curb_weight_tons": 2.6
  },
  {
    "make": "B & W CONSTRUCTION",
    "model": "B & W CONSTRUCTION TRAILER",
    "variant": "CORNICHE/BENTLEY CONTINENTAL CONVERTIBLE",
    "year": 1990,
    "curb_weight_tons": 2.6
  },
  {
    "make": "B & W CONSTRUCTION",
    "model": "B & W CONSTRUCTION TRAILER",
    "variant": "900 2DR HATCHBACK",
    "year": 1990,
    "curb_weight_tons": 1.4
  },
  {
    "make": "B & W CONSTRUCTION",
    "model": "B & W CONSTRUCTION TRAILER",
    "variant": "900 SPG 2DR HATCHBACK",
    "year": 1990,
    "curb_weight_tons": 1.5
  },
  {
    "make": "B & W CONSTRUCTION",
    "model": "B & W CONSTRUCTION TRAILER",
    "variant": "900 TURBO 2DR HATCHBACK",
    "year": 1990,
    "curb_weight_tons": 1.5
  },
  {
    "make": "B & W CONSTRUCTION",
    "model": "B & W CONSTRUCTION TRAILER",
    "variant": "900 TURBO CONVERTIBLE",
    "year": 1990,
    "curb_weight_tons": 1.5
  },
  {
    "make": "B & W CONSTRUCTION",
    "model": "B & W CONSTRUCTION TRAILER",
    "variant": "9000 SPG 4DR HATCHBACK",
    "year": 1990,
    "curb_weight_tons": 1.5
  },
  {
    "make": "B & W CONSTRUCTION",
    "model": "B & W CONSTRUCTION TRAILER",
    "variant": "CUTLASS SUPREME CONVERTIBLE",
    "year": 1990,
    "curb_weight_tons": 1.8
  },
  {
    "make": "B & W CONSTRUCTION",
    "model": "B & W CONSTRUCTION TRAILER",
    "variant": "TORONADO BASE/TROFEO 2DR COUPE",
    "year": 1990,
    "curb_weight_tons": 1.7
  },
  {
    "make": "B & W CONSTRUCTION",
    "model": "B & W CONSTRUCTION TRAILER",
    "variant": "88 ROYALE BASE/BROUGHAM 4DR SEDAN",
    "year": 1990,
    "curb_weight_tons": 1.6
  },
  {
    "make": "B & W CONSTRUCTION",
    "model": "B & W CONSTRUCTION TRAILER",
    "variant": "98 REGENCY BROUGHAM/TOURING 4DR SEDAN",
    "year": 1990,
    "curb_weight_tons": 1.7
  },
  {
    "make": "B & W CONSTRUCTION",
    "model": "B & W CONSTRUCTION TRAILER",
    "variant": "CUTLASS CIERA BASE/SL 4 DR SEDAN",
    "year": 1990,
    "curb_weight_tons": 1.4
  },
  {
    "make": "B & W CONSTRUCTION",
    "model": "B & W CONSTRUCTION TRAILER",
    "variant": "CUTLASS CRUISER BASE/SL WAGON",
    "year": 1990,
    "curb_weight_tons": 1.5
  },
  {
    "make": "B & W CONSTRUCTION",
    "model": "B & W CONSTRUCTION TRAILER",
    "variant": "CUTLASS SUPREME BASE/SL 2DR COUPE",
    "year": 1990,
    "curb_weight_tons": 1.6
  },
  {
    "make": "B & W CONSTRUCTION",
    "model": "B & W CONSTRUCTION TRAILER",
    "variant": "CUTLASS SUPREME BASE/SL 4DR SEDAN",
    "year": 1990,
    "curb_weight_tons": 1.6
  },
  {
    "make": "B & W CONSTRUCTION",
    "model": "B & W CONSTRUCTION TRAILER",
    "variant": "ELECTRA PARK AVENUE BASE/ULTRA 4DR SEDAN",
    "year": 1990,
    "curb_weight_tons": 1.6
  },
  {
    "make": "B & W CONSTRUCTION",
    "model": "B & W CONSTRUCTION TRAILER",
    "variant": "LESABRE CUSTOM/LIMITED 4DR SEDAN",
    "year": 1990,
    "curb_weight_tons": 1.6
  },
  {
    "make": "B & W CONSTRUCTION",
    "model": "B & W CONSTRUCTION TRAILER",
    "variant": "REATTA CONVERTIBLE",
    "year": 1990,
    "curb_weight_tons": 1.8
  },
  {
    "make": "B & W CONSTRUCTION",
    "model": "B & W CONSTRUCTION TRAILER",
    "variant": "325i CABRIOLET",
    "year": 1990,
    "curb_weight_tons": 1.5
  }
]